setup.py
flask_cache_external_assets/__init__.py
flask_cache_external_assets/lib.py
flask_cache_external_assets/metadata.py
flask_cache_external_assets.egg-info/PKG-INFO
flask_cache_external_assets.egg-info/SOURCES.txt
flask_cache_external_assets.egg-info/dependency_links.txt
flask_cache_external_assets.egg-info/entry_points.txt
flask_cache_external_assets.egg-info/requires.txt
flask_cache_external_assets.egg-info/top_level.txt