Metadata-Version: 1.0
Name: flask-cache-external-assets
Version: 0.2.0
Summary: Flask extension for caching external assets
Home-page: http://camembertaulaitcrew.biz
Author: CALC
Author-email: contact@camembertaulaitcrew.biz
License: MIT
Platform: UNKNOWN
Classifier: Development Status :: 3 - Alpha
Classifier: Environment :: Web Environment
Classifier: Intended Audience :: Developers
Classifier: License :: OSI Approved :: BSD License
Classifier: Operating System :: OS Independent
Classifier: Programming Language :: Python
Classifier: Topic :: Internet :: WWW/HTTP :: Dynamic Content
Classifier: Topic :: Software Development :: Libraries :: Python Modules
